{
  "Instagram - Por géneros (MUJER)": {
    "categories": {
      "Instagram - Por géneros (MUJER)": {
        "types": {
          "579 - ID 579 - Instagram - Me gusta Femenino- Max. 20k - $2.16 por 1000": {
            "pricePerUnit": 0.00216,
            "minQuantity": 10,
            "maxQuantity": 50000,
            "deliveryTime": "No especificado",
            "description": "Inicio: De 0 a 30 minutosVelocidad: 10 a 20k DiaCalidad: Buena calidad Publico: Mundo - Cuentas femeninasCaídas: Sin caidas—---------------------------------- ----Enlace: Enlace de publicaciónEjemplo: https://www.instagram.com/p/xyz",
            "features": {}
          },
          "4586 - ID 4586 - Instagram - Me gusta Mayormente Mujeres  - Max 50K  - R30 - $1.06 por 1000": {
            "pricePerUnit": 0.001056,
            "minQuantity": 20,
            "maxQuantity": 50000,
            "deliveryTime": "No especificado",
            "description": "",
            "features": {}
          },
          "578 - ID 578 - Instagram - Me gusta femenino (Brasil) - Max. 30k - $2.74 por 1000": {
            "pricePerUnit": 0.0027440000000000003,
            "minQuantity": 10,
            "maxQuantity": 100000,
            "deliveryTime": "No especificado",
            "description": "Inicio: De 0 a 30 minutosCalidad: Buena calidad Publico: Brasil - Cuentas femeninasCaídas: Sin caidas—---------------------------------- ----Enlace: Enlace de publicaciónEjemplo: https://www.instagram.com/p/xyz",
            "features": {}
          },
          "575 - ID 575 - Instagram - Me gusta femenino (USA) - Max. 6k - R30 - $33.26 por 1000": {
            "pricePerUnit": 0.033264,
            "minQuantity": 50,
            "maxQuantity": 6000,
            "deliveryTime": "30 Días",
            "description": "Inicio: De 0 a 1 horaVelocidad: 100 a 250 HoraCalidad: Buena calidad Audiencia: USA - Cuentas femeninasRecarga: 30 Días (Si cae más del 10%)—---------------------------------- ----Enlace: Enlace de publicaciónEjemplo: https://www.instagram.com/p/xyz",
            "features": {}
          },
          "644 - ID 644 - Instagram - Seguidores Femenino - Brasil - Max 10k - R30 - $18 por 1000": {
            "pricePerUnit": 0.018,
            "minQuantity": 20,
            "maxQuantity": 10000,
            "deliveryTime": "No especificado",
            "description": "",
            "features": {}
          },
          "588 - ID 588 - Instagram - Comentarios personalizados femeninos - Max. 70k - $25.98 por 1000": {
            "pricePerUnit": 0.025984,
            "minQuantity": 5,
            "maxQuantity": 70000,
            "deliveryTime": "24 horas",
            "description": "Inicio: De 0 a 24 horasCalidad: Buena calidadPublico: Mundo - Cuentas femeninasComentarios: Comentarios personalizados📌 Escriba un comentario por línea📌 No se aceptan menciones @📌 No se aceptan malas palabras o malas intenciones❌ Si el sistema detecta alguna falta, detendrá la entrega del servicio si derecho a reembolso.—--------------------------------------Enlace: Enlace de publicación de InstagramEjemplo: https://www.instagram.com/p/xyz",
            "features": {}
          }
        }
      }
    }
  }
}