{
  "Tiktok - Seguidores CON GARANTIA": {
    "categories": {
      "Tiktok - Seguidores CON GARANTIA": {
        "types": {
          "3203 - ID 3203 - TikTok - Seguidores - Max. 5M - R30 - $5.58 por 1000": {
            "pricePerUnit": 0.00558,
            "minQuantity": 10,
            "maxQuantity": 10000000,
            "deliveryTime": "12 Horas",
            "description": "Entrega de 500 a 2000+  seguidores por día\n\nInicio: De 15 minutos a 12 Horas\nVelocidad: 500 a 2000+  seguidores por día\nCalidad: Cuentas nuevas, la mayoría sin publicaciones\nAudiencia: Mundo\nCaída: Puede haber caídas en algunos pedidos\nGarantía: 30 días (Si baja más del 10%)\n👆 No olvide que estos datos son solo estimaciones (Pueden variar)\n—---------------------------------- ----\nEnlace: Enlace de cuenta de TikTok o nombre de usuario (Sin el @)\nEjemplo 1: https://www.tiktok.com/@jamesdrodriguez\nEjemplo 2: jamesdrodriguez",
            "features": {}
          },
          "2081 - ID 2081 - TikTok - Seguidores - Max. 5M - R30 - $5.58 por 1000": {
            "pricePerUnit": 0.00558,
            "minQuantity": 50,
            "maxQuantity": 1000000,
            "deliveryTime": "12  Horas",
            "description": "Inicio: De 1 a 12  Horas\nVelocidad: 1K a  5K seguidores por día\nAudiencia: Mundo\nCaída: No se esperan caídas\nGarantía: 30 días (Caídas superiores al 10%)\n👆 No olvide que estos datos son solo estimaciones (Pueden variar)\n—---------------------------------- ----\nEnlace: Enlace de cuenta de TikTok o nombre de usuario (Sin el @)\nEjemplo 1: https://www.tiktok.com/@jamesdrodriguez\nEjemplo 2: jamesdrodriguez",
            "features": {}
          },
          "4681 - ID 4681 - TikTok - Seguidores - Max 500k - R30 - $5.85 por 1000": {
            "pricePerUnit": 0.005848,
            "minQuantity": 10,
            "maxQuantity": 50000,
            "deliveryTime": "12 Horas",
            "description": "Inicio: De 1 a 12 Horas\nVelocidad: 100 a 1000+  seguidores por día\nCaída: No se esperan caídas\nCalidad: Con apariencia real\nGarantía: 30 días (Si cae mas del 10 %)\n👆 No olvide que estos datos son solo estimaciones (Pueden variar)\n—---------------------------------- ----\nEnlace: Enlace de cuenta de TikTok \nEjemplo 1: https://www.tiktok.com/@jamesdrodriguez",
            "features": {}
          },
          "3982 - ID 3982 - TikTok - Seguidores - Max. 50K - R30 - $6.05 por 1000": {
            "pricePerUnit": 0.006048,
            "minQuantity": 10,
            "maxQuantity": 50000,
            "deliveryTime": "12 Horas",
            "description": "Inicio: De 1 a 12 HorasVelocidad: 100 a 1000+  seguidores por díaCaída: No se esperan caídasGarantía: 30 días (Si cae mas del 10 %)👆 No olvide que estos datos son solo estimaciones (Pueden variar)—---------------------------------- ----Enlace: Enlace de cuenta de TikTok Ejemplo 1: https://www.tiktok.com/@jamesdrodriguez",
            "features": {}
          },
          "2114 - ID 2114 - TikTok - Seguidores - Max. 500K - R30 🐌 LENTO - $5.40 por 1000": {
            "pricePerUnit": 0.0054,
            "minQuantity": 10,
            "maxQuantity": 500000,
            "deliveryTime": "12 Horas",
            "description": "Inicio: De 1 a 12 HorasVelocidad: 2K a  10K+  seguidores por díaCalidad: Cuentas mixtasAudiencia: MundoCancelar: Botón de cancelar activoCaída: 5 al 8%Garantía: 30 Dias (Si cae mas del 10%)👆 No olvide que estos datos son solo estimaciones (Pueden variar)—---------------------------------- ----Enlace: Enlace de cuenta de TikTok o nombre de usuario (Sin el @)Ejemplo 1: https://www.tiktok.com/@jamesdrodriguezEjemplo 2: jamesdrodriguez",
            "features": {}
          },
          "3683 - ID 3683 - TikTok - Seguidores - Max. 50k - R60 - $8.80 por 1000": {
            "pricePerUnit": 0.0088,
            "minQuantity": 50,
            "maxQuantity": 50000,
            "deliveryTime": "12 Horas",
            "description": "Inicio: De 1 a 12 Horas\nVelocidad: 500 a 2K por día\nCalidad: Cuentas con foto de perfil, algunas con publicaciones\nAudiencia: Mundo\nCaída: 4% a 5%\nGarantía: 60 días (Si baja más del 10%)\n👆 No olvide que estos datos son solo estimaciones (Pueden variar)\n—---------------------------------- ----\nEnlace: Enlace de cuenta de TikTok o nombre de usuario (Sin el @)\nEjemplo 1: https://www.tiktok.com/@jamesdrodriguez\nEjemplo 2: jamesdrodriguez",
            "features": {}
          },
          "4686 - ID 4686 - TikTok - Seguidores - Max 100k - R60 - $8.80 por 1000": {
            "pricePerUnit": 0.0088,
            "minQuantity": 10,
            "maxQuantity": 100000,
            "deliveryTime": "12 Horas",
            "description": "Probar primero la calidad con cantidades pequeñas\n\nInicio: De 1 a 12 Horas\nVelocidad: 2K a  5K por día\nCalidad: baja/media calidad\nAudiencia: Mundo\nGarantía: 60 días (Si cae más del 10%)\n\n👆 No olvide que estos datos son solo estimaciones (Pueden variar)\n—-----------------------------------------------------------------------------------------\nEnlace: Enlace de cuenta de TikTok o nombre de usuario (Sin el @)\nEjemplo 1: https://www.tiktok.com/@jamesdrodriguez\nEjemplo 2: jamesdrodriguez",
            "features": {}
          },
          "4792 - ID 4792 - TikTok - Seguidores - Max 1M - R30 - ⚡️ - $9.10 por 1000": {
            "pricePerUnit": 0.0091,
            "minQuantity": 10,
            "maxQuantity": 1000000,
            "deliveryTime": "12 Horas",
            "description": "ENTREGA DE 100 A 1000+ POR DÍA\n\nInicio: De 1 a 12 Horas\nVelocidad: 100 a 1000+  seguidores por día\nCalidad: Cuentas con foto de perfil \nAudiencia: Mundial\nCaída: No se esperan caídas\nGarantía: 30 días (Solo aplica para enlaces nuevos)\n👆 No olvide que estos datos son solo estimaciones (Pueden variar)\n—---------------------------------- ----\nEnlace: Enlace de cuenta de TikTok o nombre de usuario (Sin el @)\nEjemplo 1: https://www.tiktok.com/@jamesdrodriguez\nEjemplo 2: jamesdrodriguez",
            "features": {}
          },
          "3981 - ID 3981 -TikTok - Seguidores - Max 5K - R30 - RAPIDO - $9.38 por 1000": {
            "pricePerUnit": 0.009380000000000001,
            "minQuantity": 10,
            "maxQuantity": 5000,
            "deliveryTime": "12 Horas",
            "description": "Inicio: De 1 a 12 Horas\nVelocidad: 5K seguidores por día\nCaída: No se esperan caídas\nGarantía: 30 días (Si cae mas del 10 %)\n👆 No olvide que estos datos son solo estimaciones (Pueden variar)\n—---------------------------------- ----\nEnlace: Enlace de cuenta de TikTok \nEjemplo 1: https://www.tiktok.com/@jamesdrodriguez",
            "features": {}
          },
          "4795 - ID 4795 - TikTok - Seguidores - Max 1M - R30 - ⚡️ - $10.00 por 1000": {
            "pricePerUnit": 0.010002,
            "minQuantity": 10,
            "maxQuantity": 1000000,
            "deliveryTime": "12 Horas",
            "description": "Inicio: De 1 a 12 Horas\nVelocidad: 100 a 1000+  seguidores por día\nCalidad: Cuentas con foto de perfil \nAudiencia: Mundial\nCaída: No se esperan caídas\nGarantía: 30 días (Solo aplica para enlaces nuevos)\n👆 No olvide que estos datos son solo estimaciones (Pueden variar)\n—---------------------------------- ----\nEnlace: Enlace de cuenta de TikTok o nombre de usuario (Sin el @)\nEjemplo 1: https://www.tiktok.com/@jamesdrodriguez\nEjemplo 2: jamesdrodriguez",
            "features": {}
          },
          "4794 - ID 4794 - TikTok - Seguidores - Max 100K - R30 - ⚡️ - $10.77 por 1000": {
            "pricePerUnit": 0.01077,
            "minQuantity": 10,
            "maxQuantity": 100000,
            "deliveryTime": "12 Horas",
            "description": "Inicio: De 1 a 12 Horas\nVelocidad: 100 a 1000+  seguidores por día\nCalidad: Cuentas con foto de perfil \nAudiencia: Mundial\nCaída: No se esperan caídas\nGarantía: 30 días (Solo aplica para enlaces nuevos)\n👆 No olvide que estos datos son solo estimaciones (Pueden variar)\n—---------------------------------- ----\nEnlace: Enlace de cuenta de TikTok o nombre de usuario (Sin el @)\nEjemplo 1: https://www.tiktok.com/@jamesdrodriguez\nEjemplo 2: jamesdrodriguez",
            "features": {}
          },
          "2080 - ID 2080 - TikTok - Seguidores - Max 50k - R30 - ⚡ - $11.34 por 1000": {
            "pricePerUnit": 0.01134,
            "minQuantity": 10,
            "maxQuantity": 50000,
            "deliveryTime": "4 Horas",
            "description": "ENTREGA DE 100 A 1000+ POR DÍAInicio: De 1 a 4 HorasVelocidad: 100 a 1000+  seguidores por díaCalidad: Cuentas con foto de perfil, algunas con publicacionesAudiencia: MundoCaída: No se esperan caídasGarantía: 30 días (Solo aplica para enlaces nuevos)👆 No olvide que estos datos son solo estimaciones (Pueden variar)—---------------------------------- ----Enlace: Enlace de cuenta de TikTok o nombre de usuario (Sin el @)Ejemplo 1: https://www.tiktok.com/@jamesdrodriguezEjemplo 2: jamesdrodriguez",
            "features": {}
          },
          "4788 - ID 4788 - TikTok - Seguidores - Max. 50K - R30 - $12.30 por 1000": {
            "pricePerUnit": 0.0123,
            "minQuantity": 10,
            "maxQuantity": 50000,
            "deliveryTime": "12 Horas",
            "description": "Inicio: De 1 a 12 Horas\nVelocidad: 200K a 2K por día\nCalidad: Cuentas con foto de perfil, algunas con publicaciones\nAudiencia: Mundo\nCaída: 4% a 5%\nGarantía: 30 días (Si baja más del 10%)\n👆 No olvide que estos datos son solo estimaciones (Pueden variar)\n—---------------------------------- ----\nEnlace: Enlace de cuenta de TikTok o nombre de usuario (Sin el @)\nEjemplo 1: https://www.tiktok.com/@jamesdrodriguez\nEjemplo 2: jamesdrodriguez",
            "features": {}
          },
          "2194 - ID 2194 - TikTok - Seguidores con apariencia real - Max 10k - R30 - $12.88 por 1000": {
            "pricePerUnit": 0.01288,
            "minQuantity": 10,
            "maxQuantity": 50000,
            "deliveryTime": "12 Horas",
            "description": "Inicio: De 1 a 12 HorasVelocidad: 300 a 500+  seguidores por díaCalidad: Cuentas con foto de perfil, algunas con publicacionesAudiencia: MundoCaída: 4% a 6%Garantía: 30 días (Si baja más del 10%) Solo para enlaces nuevos👆 No olvide que estos datos son solo estimaciones (Pueden variar)—---------------------------------- ----Enlace: Enlace de cuenta de TikTok o nombre de usuario (Sin el @)Ejemplo 1: https://www.tiktok.com/@jamesdrodriguezEjemplo 2: jamesdrodriguez",
            "features": {}
          },
          "4593 - ID 4593 - TikTok - Seguidores con apariencia real - Max. 24K - $12.99 por 1000": {
            "pricePerUnit": 0.012988,
            "minQuantity": 10,
            "maxQuantity": 100000,
            "deliveryTime": "12 Horas",
            "description": "Inicio: De 1 a 12 Horas\nVelocidad: 2K a  5+K seguidores por día\nCalidad: Cuentas con apariencia real\nAudiencia: Mundo\nCaída: No se esperan caídas\nGarantía: 30 días (Solo aplica para enlaces nuevos)\n👆 No olvide que estos datos son solo estimaciones (Pueden variar)\n—---------------------------------- ----\nEnlace: Enlace de cuenta de TikTok o nombre de usuario (Sin el @)\nEjemplo 1: https://www.tiktok.com/@jamesdrodriguez\nEjemplo 2: jamesdrodriguez",
            "features": {}
          },
          "4793 - ID 4793 - TikTok - Seguidores - Max 500K - R30 - ⚡️ - $14.03 por 1000": {
            "pricePerUnit": 0.014028,
            "minQuantity": 100,
            "maxQuantity": 500000,
            "deliveryTime": "12 Horas",
            "description": "Inicio: De 1 a 12 Horas\nVelocidad: 100 a 1000+  seguidores por día\nCalidad: Cuentas con foto de perfil \nAudiencia: Mundial\nCaída: No se esperan caídas\nGarantía: 30 días (Solo aplica para enlaces nuevos)\n👆 No olvide que estos datos son solo estimaciones (Pueden variar)\n—---------------------------------- ----\nEnlace: Enlace de cuenta de TikTok o nombre de usuario (Sin el @)\nEjemplo 1: https://www.tiktok.com/@jamesdrodriguez\nEjemplo 2: jamesdrodriguez",
            "features": {}
          }
        }
      }
    }
  }
}